MANIFEST.in
board_hr_timesheet_view.xml
hr_timesheet_sheet_data.xml
hr_timesheet_sheet_demo.xml
hr_timesheet_sheet_view.xml
hr_timesheet_workflow.xml
res_config_view.xml
setup.py
./__init__.py
./__openerp__.py
./hr_timesheet_sheet.py
./res_config.py
./report/__init__.py
./report/hr_timesheet_report.py
./report/timesheet_report.py
./wizard/__init__.py
./wizard/hr_timesheet_current.py
i18n/ar.po
i18n/bg.po
i18n/bs.po
i18n/ca.po
i18n/cs.po
i18n/da.po
i18n/de.po
i18n/el.po
i18n/es.po
i18n/es_AR.po
i18n/es_CR.po
i18n/es_EC.po
i18n/es_MX.po
i18n/es_VE.po
i18n/et.po
i18n/fi.po
i18n/fr.po
i18n/hr.po
i18n/hr_timesheet_sheet.pot
i18n/hu.po
i18n/id.po
i18n/it.po
i18n/ja.po
i18n/ko.po
i18n/lt.po
i18n/lv.po
i18n/mk.po
i18n/mn.po
i18n/nl.po
i18n/nl_BE.po
i18n/oc.po
i18n/pl.po
i18n/pt.po
i18n/pt_BR.po
i18n/ro.po
i18n/ru.po
i18n/sk.po
i18n/sl.po
i18n/sq.po
i18n/sv.po
i18n/th.po
i18n/tlh.po
i18n/tr.po
i18n/uk.po
i18n/vi.po
i18n/zh_CN.po
i18n/zh_TW.po
images/hr_my_current_timesheet.jpeg
images/hr_timesheet_activity.jpeg
images/hr_timesheet_analysis.jpeg
images/hr_timesheet_sheet_analysis.jpeg
openerp_hr_timesheet_sheet.egg-info/PKG-INFO
openerp_hr_timesheet_sheet.egg-info/SOURCES.txt
openerp_hr_timesheet_sheet.egg-info/dependency_links.txt
openerp_hr_timesheet_sheet.egg-info/requires.txt
openerp_hr_timesheet_sheet.egg-info/top_level.txt
process/hr_timesheet_sheet_process.xml
report/hr_timesheet_report_view.xml
report/timesheet_report_view.xml
security/hr_timesheet_sheet_security.xml
security/ir.model.access.csv
static/src/img/icon.png
static/src/js/timesheet.js
static/src/xml/timesheet.xml
test/test_hr_timesheet_sheet.yml
wizard/hr_timesheet_current_view.xml